{
  "api": {
    "name": "YPushPlugin",
    "slug": "ypushplugin",
    "docs": "",
    "tags": [],
    "methods": [
      {
        "name": "getNotificationSettings",
        "signature": "() => Promise<{ data: number; }>",
        "parameters": [],
        "returns": "Promise<{ data: number; }>",
        "tags": [],
        "docs": "",
        "complexTypes": [],
        "slug": "getnotificationsettings"
      },
      {
        "name": "requestAuthorization",
        "signature": "() => Promise<{ data: boolean; }>",
        "parameters": [],
        "returns": "Promise<{ data: boolean; }>",
        "tags": [],
        "docs": "",
        "complexTypes": [],
        "slug": "requestauthorization"
      },
      {
        "name": "getDeviceToken",
        "signature": "() => Promise<{ data: string; }>",
        "parameters": [],
        "returns": "Promise<{ data: string; }>",
        "tags": [],
        "docs": "",
        "complexTypes": [],
        "slug": "getdevicetoken"
      },
      {
        "name": "openSettings",
        "signature": "() => Promise<{ data: boolean; }>",
        "parameters": [],
        "returns": "Promise<{ data: boolean; }>",
        "tags": [],
        "docs": "",
        "complexTypes": [],
        "slug": "opensettings"
      },
      {
        "name": "setBadge",
        "signature": "(options: { value: number; }) => Promise<{ data: boolean; }>",
        "parameters": [
          {
            "name": "options",
            "docs": "",
            "type": "{ value: number; }"
          }
        ],
        "returns": "Promise<{ data: boolean; }>",
        "tags": [],
        "docs": "",
        "complexTypes": [],
        "slug": "setbadge"
      }
    ],
    "properties": []
  },
  "interfaces": [],
  "enums": [],
  "typeAliases": [],
  "pluginConfigs": []
}